Workbook

Sheet README
B2: Smart Waste Sorting Bin — BOM & Cost Workbook
B3: 智能分類垃圾桶 — 物料清單與成本工作簿
B4: Version 1.0 · 29 October 2026 · Prices in HKD · Indicative only
B6: Purpose | C6: Costed bill of materials for the recommended four-stream build, with tools, pin map and cut list.
B7: Currency | C7: Hong Kong dollars (HKD). Prices are indicative Hong Kong / Taobao street prices in October 2026.
B8: Recommended total | C8: See the BOM sheet total. Add 15% for shipping, tax and spares.
B9: Lean build | C9: ≈ HK$3,200: HC-SR04 instead of 4 × VL53L1X; 12 V adapter instead of battery; reuse bins; no gas struts; no SHT31/metal kit.
B10: Enhanced build | C10: ≈ HK$4,800: Pi 4 2 GB; aluminium frame; spare servo/stepper; better camera; UPS.
B11: How to edit | C11: Change Qty or Unit price; line totals and the total update automatically. The Budget sheet uses SUMIF on the BOM.
B12: Safety | C12: Use a certified Li-ion pack with BMS, a 5 A fuse, a main switch and an e-stop. Charge outside the bin. Do not use loose cells.
B13: Academic | C13: Keep receipts and a logbook. Prices change; verify before ordering.
B15: Priority | C15: Core = needed for the four-stream sorter; Optional = evidence/reliability upgrade, can be omitted in the lean build.

Sheet BOM
A1: Bill of Materials — recommended build
A2: All prices HKD, indicative. Edit Qty/Unit; Total is a formula. Core vs Optional is shown in the last column.
A4: ID | B4: Group | C4: Item (EN) | D4: Item (ZH) | E4: Specification | F4: Qty | G4: Unit (HKD) | H4: Total (HKD) | I4: Source | J4: Notes (EN) | K4: Notes (ZH) | L4: Priority
A5: S-01 | B5: Structure | C5: Plywood sheet, 18 mm | D5: 18 mm 夾板 | E5: 1220 x 2440 mm, B/BB or marine ply | F5: 1 | G5: 380 | H5: =F5*G5 -> 380 | I5: Local wood shop | J5: Frame, drawer, lid; cut list in Appendix B | K5: 框架、抽屜、蓋；切割表見附錄 B | L5: Core
A6: S-02 | B6: Structure | C6: PP / acrylic sheet, 3 mm | D6: 3 mm PP／亞克力板 | E6: 600 x 400 mm, food-contact PP preferred | F6: 4 | G6: 45 | H6: =F6*G6 -> 180 | I6: Local plastics shop / Taobao | J6: Hopper liner, spout guard, drip shields | K6: 料斗內襯、滑槽護板、滴水擋板 | L6: Core
A7: S-03 | B7: Structure | C7: Piano hinge, 500 mm | D7: 鋼琴鉸鏈 500 mm | E7: Stainless steel, 32 mm open width | F7: 2 | G7: 25 | H7: =F7*G7 -> 50 | I7: Hardware shop | J7: Lid and hopper door | K7: 蓋與料斗門 | L7: Core
A8: S-04 | B8: Structure | C8: Drawer slides, 450 mm | D8: 抽屜滑軌 450 mm | E8: 3-fold, 45 kg rated, pair | F8: 2 | G8: 60 | H8: =F8*G8 -> 120 | I8: Hardware shop | J8: One pair for the bin drawer | K8: 垃圾桶抽屜一對 | L8: Core
A9: S-05 | B9: Structure | C9: Gas strut, 60 N | D9: 氣壓撐桿 60 N | E9: 250 mm extended, 10 mm ball ends | F9: 2 | G9: 40 | H9: =F9*G9 -> 80 | I9: Hardware shop | J9: Lid assist and stay | K9: 協助開蓋及定位 | L9: Core
A10: S-06 | B10: Structure | C10: Rubber feet | D10: 橡膠腳墊 | E10: 30 mm diameter, M6 thread | F10: 4 | G10: 5 | H10: =F10*G10 -> 20 | I10: Hardware shop | J10: Vibration and floor protection | K10: 減震及保護地板 | L10: Core
A11: S-07 | B11: Structure | C11: Fixings assortment | D11: 緊固件組合 | E11: M4/M5 bolts, nuts, washers, inserts, angle brackets | F11: 1 | G11: 150 | H11: =F11*G11 -> 150 | I11: Hardware shop | J11: Allow 20% spare | K11: 預留 20% 備用 | L11: Core
A12: S-08 | B12: Structure | C12: Silicone seal strip | D12: 矽膠密封條 | E12: 10 x 3 mm, self-adhesive, 3 m | F12: 1 | G12: 30 | H12: =F12*G12 -> 30 | I12: Hardware shop | J12: Hopper door and lid gasket | K12: 料斗門及蓋密封 | L12: Core
A13: S-09 | B13: Structure | C13: Storage bins, 12 L | D13: 12 L 收納箱 | E13: Approx. 190 x 190 x 360 mm, PP, 4 pcs | F13: 4 | G13: 40 | H13: =F13*G13 -> 160 | I13: Japan Home / Taobao | J13: Cut an 80 x 80 mm inner-corner notch | K13: 內角切 80 x 80 mm 缺口 | L13: Core
A14: S-10 | B14: Structure | C14: PETG filament | D14: PETG 線材 | E14: 1.75 mm, 1 kg, black | F14: 1 | G14: 120 | H14: =F14*G14 -> 120 | I14: 3D printing shop | J14: Camera bracket, sensor mounts, spout collar | K14: 鏡頭支架、感測器座、滑槽環 | L14: Core
A15: S-11 | B15: Structure | C15: Adhesive and sealant | D15: 膠水及密封膠 | E15: Epoxy, acrylic cement, neutral silicone | F15: 1 | G15: 60 | H15: =F15*G15 -> 60 | I15: Hardware shop | J15: Do not use silicone on load cells | K15: 負重感測器附近勿用矽膠 | L15: Core
A16: S-12 | B16: Structure | C16: Matte black paint | D16: 啞黑噴漆 | E16: 400 ml, low sheen | F16: 1 | G16: 45 | H16: =F16*G16 -> 45 | I16: Hardware shop | J16: Inside hopper to reduce glare | K16: 料斗內部減少反光 | L16: Core
... A62: A-10 | B62: Assembly | C62: Bin liners / cleaning kit | D62: 垃圾桶袋／清潔組 | E62: Compostable liners, wipes, gloves | F62: 1 | G62: 40 | H62: =F62*G62 -> 40 | I62: Supermarket | J62: Hygiene and demo readiness | K62: 衛生及演示準備 | L62: Core
A63: TOTAL / 合計 | H63: =SUM(H5:H62) -> 4050

Sheet Budget
B2: Budget summary / 預算摘要
B3: Group totals use SUMIF on the BOM sheet. The total is the same as the BOM total.
B5: Group | C5: Cost (HKD) | D5: Share | E5: Comment
B6: Structure | C6: =SUMIF(BOM!$B$5:$B$62,B6,BOM!$H$5:$H$62) -> 1395 | D6: =C6/$C$11 -> 0.34444444
B7: Motion | C7: =SUMIF(BOM!$B$5:$B$62,B7,BOM!$H$5:$H$62) -> 490 | D7: =C7/$C$11 -> 0.12098765
B8: Sensing | C8: =SUMIF(BOM!$B$5:$B$62,B8,BOM!$H$5:$H$62) -> 1030 | D8: =C8/$C$11 -> 0.25432099
B9: Power | C9: =SUMIF(BOM!$B$5:$B$62,B9,BOM!$H$5:$H$62) -> 700 | D9: =C9/$C$11 -> 0.17283951
B10: Assembly | C10: =SUMIF(BOM!$B$5:$B$62,B10,BOM!$H$5:$H$62) -> 435 | D10: =C10/$C$11 -> 0.10740741
B11: TOTAL | C11: =SUM(C6:C10) -> 4050 | D11: 1 | E11: Recommended build, before 15% contingency.
B14: Build tier | C14: Cost (HKD) | D14: What changes
B15: Lean | C15: 3200 | D15: HC-SR04; 12 V adapter; reuse bins; plywood offcuts; no gas struts; no SHT31/metal kit.
B16: Recommended | C16: =C11 -> 4050 | D16: As listed in the BOM; battery + adapter; 4 × VL53L1X; metal kit; gas struts.
B17: Enhanced | C17: 4800 | D17: Pi 4 2 GB; aluminium frame; spare servo/stepper; better camera; UPS.
B19: Recommended practice: add 15% contingency for shipping, tax, broken parts and one spare sensor. Keep every receipt for the final report.

Sheet Tools
A1: Tools and workshop equipment
A2: If the lab already has these, budget only for consumables. The fire bag and safety glasses are not optional.
A4: ID | B4: Tool (EN) | C4: Tool (ZH) | D4: Qty | E4: Unit (HKD) | F4: Total (HKD)
A5: T-01 | B5: Soldering iron + stand + solder | C5: 烙鐵＋架＋焊錫 | D5: 1 | E5: 180 | F5: =D5*E5 -> 180
A6: T-02 | B6: Digital multimeter | C6: 數位萬用表 | D6: 1 | E6: 150 | F6: =D6*E6 -> 150
A7: T-03 | B7: Wire strippers / crimping tool | C7: 剝線鉗／壓線鉗 | D7: 1 | E7: 120 | F7: =D7*E7 -> 120
A8: T-04 | B8: Electric drill + bits + hole saw | C8: 電鑽＋鑽頭＋孔鋸 | D8: 1 | E8: 350 | F8: =D8*E8 -> 350
A9: T-05 | B9: Jigsaw or circular saw | C9: 曲線鋸或圓鋸 | D9: 1 | E9: 300 | F9: =D9*E9 -> 300
A10: T-06 | B10: Screwdriver and hex key set | C10: 螺絲批及內六角套裝 | D10: 1 | E10: 120 | F10: =D10*E10 -> 120
A11: T-07 | B11: Digital calipers | C11: 數位卡尺 | D11: 1 | E11: 80 | F11: =D11*E11 -> 80
A12: T-08 | B12: Hot glue gun | C12: 熱熔膠槍 | D12: 1 | E12: 80 | F12: =D12*E12 -> 80
A13: T-09 | B13: Safety glasses and gloves | C13: 護目鏡及手套 | D13: 1 | E13: 60 | F13: =D13*E13 -> 60
A14: T-10 | B14: Li-ion fire bag | C14: 鋰電池防火袋 | D14: 1 | E14: 80 | F14: =D14*E14 -> 80
A15: TOTAL TOOLS / 工具合計 | F15: =SUM(F5:F14) -> 1520

Sheet Pins
A1: ESP32 pin map
A2: Authoritative pin schedule for the recommended build. GPIO34-39 are input-only.
A4: Signal | B4: ESP32 pin | C4: Type | D4: Device / bus | E4: Notes
A5: I2C SDA | B5: GPIO21 | C5: Bidirectional | D5: SHT31, VL53L0X, 4 x VL53L1X, PCF8574 | E5: 4.7 k pull-up to 3.3 V; assign ToF addresses with XSHUT
A6: I2C SCL | B6: GPIO22 | C6: Bidirectional | D6: Same I2C bus | E6: Keep leads < 500 mm; twisted pair
A7: HX711 DOUT | B7: GPIO32 | C7: Input | D7: HX711 | E7: 10 Hz or 80 Hz; shielded cable
A8: HX711 SCK | B8: GPIO33 | C8: Output | D8: HX711 | E8: Keep away from stepper wires
A9: Stepper STEP | B9: GPIO25 | C9: Output | D9: A4988 STEP | E9: 1/8 microstep; 1200 steps per 90 deg
A10: Stepper DIR | B10: GPIO26 | C10: Output | D10: A4988 DIR | E10: Direction; always approach target clockwise
A11: Stepper EN | B11: GPIO27 | C11: Output | D11: A4988 EN | E11: Active low; disable when idle to reduce heat
A12: Hopper servo | B12: GPIO13 | C12: PWM 50 Hz | D12: DS3225MG signal | E12: 6 V supply; common ground; 1000 uF
A13: IR receiver | B13: GPIO35 | C13: Input only | D13: TSOP38238 OUT | E13: External 10 k pull-up; 100 nF decoupling
A14: E-stop status | B14: GPIO34 | C14: Input only | D14: Optocoupler / divider | E14: External 10 k pull-up; low = pressed
A15: Front button | B15: GPIO39 | C15: Input only | D15: Push button to GND | E15: External 10 k pull-up; debounce 30 ms
... A24: Spare / fan | B24: GPIO12 | C24: Output | D24: Fan MOSFET | E24: Avoid strapping conflict; fan on during sorting

Sheet Cut list
A1: Cut list
A2: Nominal dimensions. Add 1-2 mm clearance; sand to fit. Seal all plywood edges.
A4: ID | B4: Part | C4: Material | D4: Size (mm) | E4: Qty | F4: Notes
A5: C-01 | B5: Base panel | C5: 18 mm plywood | D5: 480 x 480 | E5: 1 | F5: Electronics bay floor; 20 mm feet
A6: C-02 | B6: Base front/back | C6: 18 mm plywood | D6: 480 x 100 | E6: 2 | F6: Electronics bay; vent holes
A7: C-03 | B7: Base sides | C7: 18 mm plywood | D7: 444 x 100 | E7: 2 | F7: Between front and back
A8: C-04 | B8: Bin section sides | C8: 18 mm plywood | D8: 480 x 400 | E8: 2 | F8: Left/right; drawer opening
A9: C-05 | B9: Bin section back | C9: 18 mm plywood | D9: 444 x 400 | E9: 1 | F9: Fixed back
A10: C-06 | B10: Bin section top/bottom | C10: 18 mm plywood | D10: 480 x 480 | E10: 2 | F10: Mid-frame and bin top
A11: C-07 | B11: Drawer bottom | C11: 18 mm plywood | D11: 456 x 456 | E11: 1 | F11: 4 bin pockets; 6 mm clearance
A12: C-08 | B12: Drawer sides | C12: 18 mm plywood | D12: 456 x 360 | E12: 2 | F12: Bin retaining walls
A13: C-09 | B13: Drawer front | C13: 18 mm plywood | D13: 480 x 400 | E13: 1 | F13: Handle and latch
A14: C-10 | B14: Hopper sides | C14: 18 mm plywood | D14: 360 x 300 | E14: 2 | F14: Support frame; PP liner inside
A15: C-11 | B15: Hopper front/back | C15: 18 mm plywood | D15: 324 x 300 | E15: 2 | F15: Front has door opening
A16: C-12 | B16: Hopper support plate | C16: 18 mm plywood | D16: 360 x 360 | E16: 1 | F16: Rests on 4 load cells; 180 mm center hole
... A22: C-18 | B22: Drip tray | C22: 3 mm PP | D22: 456 x 456 | E22: 1 | F22: Removable; 20 mm lip

Sheet Schedule
A1: 24-week build schedule
A2: Adjust to your actual semester dates. Keep 1-week buffers after assembly, integration and before submission.
A4: Weeks | B4: Dates | C4: Task | D4: Output / milestone
A5: 1-2 | B5: 2-15 Nov 2026 | C5: Finalise design, BOM, order long-lead parts, proposal slides | D5: Proposal ready
A6: 3-4 | B6: 16-29 Nov | C6: Cut frame/drawer, build bins, bench electronics | D6: Frame and drawer
A7: 5-6 | B7: 30 Nov-13 Dec | C7: Hopper, door, load cells, spout, bearing | D7: First mechanical assembly
A8: 7-8 | B8: 14-27 Dec | C8: ESP32 firmware, sensors, stepper/servo, serial protocol | D8: Subsystems work on bench
A9: 9-10 | B9: 28 Dec-10 Jan 2027 | C9: Dataset collection, model training, interim report | D9: Interim report 1st submission
A10: 11-12 | B10: 11-24 Jan | C10: Integrate vision, first end-to-end sort | D10: First automatic sort
A11: 13-14 | B11: 25 Jan-7 Feb | C11: Calibration, 4-class test, fix jams | D11: 50% target accuracy
A12: 15-16 | B12: 8-21 Feb | C12: PWA, bin levels, cloud, progress review prep | D12: App dashboard
A13: 17-18 | B13: 22 Feb-7 Mar | C13: 50-item test, reliability, safety, video | D13: Test report v1
A14: 19-20 | B14: 8-21 Mar | C14: Refinement, enclosure, labels, user test | D14: Demo-ready
A15: 21-22 | B15: 22 Mar-4 Apr | C15: Final testing, report draft, poster | D15: Report draft
... A17: - | B17: 27 Apr 2027 | C17: Final deadline | D17: Submit
